idloc.py
idloc-0.2.0.dist-info/METADATA
idloc-0.2.0.dist-info/WHEEL
idloc-0.2.0.dist-info/entry_points.txt
idloc-0.2.0.dist-info/licenses/LICENSE
idloc-0.2.0.dist-info/RECORD
