Metadata-Version: 2.4
Name: idloc
Version: 0.2.0
Summary: Find and get readable JSON-LD from Library of Congress Linked Data Service
Project-URL: homepage, https://github.com/edsu/idloc
License: The MIT License (MIT)
License-File: LICENSE
Requires-Python: >=3.12
Requires-Dist: beautifulsoup4>=4.13.3
Requires-Dist: click>=8.1.8
Requires-Dist: pyld>=2.0.4
Requires-Dist: requests>=2.32.3
